django_postcode_lookup/__init__.py
django_postcode_lookup/loading.py
django_postcode_lookup/serializers.py
django_postcode_lookup/urls.py
django_postcode_lookup/views.py
django_postcode_lookup/backends/__init__.py
django_postcode_lookup/backends/apiwise.py
django_postcode_lookup/backends/base.py
django_postcode_lookup/backends/postcodeapinu.py
django_postcode_lookup/backends/webservices.py
django_postcode_lookup/utils/__init__.py
django_postcode_lookup/utils/version.py
django_postcode_lookup-1.0.1.dist-info/LICENSE
django_postcode_lookup-1.0.1.dist-info/METADATA
django_postcode_lookup-1.0.1.dist-info/WHEEL
django_postcode_lookup-1.0.1.dist-info/top_level.txt
django_postcode_lookup-1.0.1.dist-info/RECORD
