Metadata-Version: 2.1
Name: django-postcode-lookup
Version: 1.0.1
Summary: Pluggable postcode lookup endpoint
Home-page: https://github.com/labd/django-postcode-lookup
Author: Michael van Tellingen
Author-email: michaelvantellingen@gmail.com
License: MIT
Keywords: postcode,api,validation
Platform: UNKNOWN
Classifier: Development Status :: 5 - Production/Stable
Classifier: Environment :: Web Environment
Classifier: Framework :: Django
Classifier: Framework :: Django :: 3.2
Classifier: License :: OSI Approved :: MIT License
Classifier: Programming Language :: Python
Classifier: Programming Language :: Python :: 3.7
Classifier: Programming Language :: Python :: 3.8
Classifier: Programming Language :: Python :: 3.9
Requires-Dist: Django (<4,>=3.2)
Requires-Dist: attrs
Requires-Dist: djangorestframework (<4,>=3)
Requires-Dist: requests (>=2.7)
Provides-Extra: docs
Requires-Dist: sphinx (>=1.5.2) ; extra == 'docs'
Provides-Extra: test
Requires-Dist: freezegun (==1.1.0) ; extra == 'test'
Requires-Dist: pretend (==1.0.9) ; extra == 'test'
Requires-Dist: pytest-cov (==2.11.1) ; extra == 'test'
Requires-Dist: pytest-django (==4.1.0) ; extra == 'test'
Requires-Dist: pytest (==6.1.2) ; extra == 'test'
Requires-Dist: requests-mock (==1.8.0) ; extra == 'test'
Requires-Dist: coverage (==5.3) ; extra == 'test'
Requires-Dist: isort (<5) ; extra == 'test'
Requires-Dist: flake8 (==3.8.4) ; extra == 'test'
Requires-Dist: flake8-blind-except (==0.1.1) ; extra == 'test'
Requires-Dist: flake8-debugger (==3.2.1) ; extra == 'test'
